{
  "collectionName": "components_appracadabra_components_customize_descriptions",
  "info": {
    "displayName": "Customize-Description",
    "description": ""
  },
  "options": {},
  "attributes": {
    "description": {
      "type": "text"
    },
    "fontSize": {
      "type": "enumeration",
      "enum": [
        "text-xs",
        "text-sm",
        "text-base",
        "text-lg",
        "text-xl",
        "text-2xl",
        "text-3xl",
        "text-4xl",
        "text-5xl",
        "text-6xl",
        "text-7xl",
        "text-8xl",
        "text-9xl"
      ]
    },
    "lineSpacing": {
      "type": "enumeration",
      "enum": [
        "tracking-tighter\t",
        "tracking-tight",
        "tracking-normal",
        "tracking-wide",
        "tracking-wider",
        "tracking-widest"
      ]
    }
  }
}
